<?xml version="1.0" encoding="UTF-8" ?>
<!DOCTYPE mapper PUBLIC "-//mybatis.org//DTD Mapper 3.0//EN" "http://mybatis.org/dtd/mybatis-3-mapper.dtd" >
<mapper namespace="com.cn.ssm.dao.PhoneLoginMapper" >
  <resultMap id="BaseResultMap" type="com.cn.ssm.entity.PhoneLogin" >
    <!--
      WARNING - @mbggenerated
      This element is automatically generated by MyBatis Generator, do not modify.
    -->
    <id column="phone" property="phone" jdbcType="VARCHAR" />
    <result column="aKey" property="akey" jdbcType="INTEGER" />
  </resultMap>
  <sql id="Base_Column_List" >
    <!--
      WARNING - @mbggenerated
      This element is automatically generated by MyBatis Generator, do not modify.
    -->
    phone, aKey
  </sql>
  <select id="selectByPrimaryKey" resultMap="BaseResultMap" parameterType="java.lang.String" >
    <!--
      WARNING - @mbggenerated
      This element is automatically generated by MyBatis Generator, do not modify.
    -->
    select 
    <include refid="Base_Column_List" />
    from phoneLogin
    where phone = #{phone,jdbcType=VARCHAR}
  </select>
  <delete id="deleteByPrimaryKey" parameterType="java.lang.String" >
    <!--
      WARNING - @mbggenerated
      This element is automatically generated by MyBatis Generator, do not modify.
    -->
    delete from phoneLogin
    where phone = #{phone,jdbcType=VARCHAR}
  </delete>
  <insert id="insert" parameterType="com.cn.ssm.entity.PhoneLogin" >
    <!--
      WARNING - @mbggenerated
      This element is automatically generated by MyBatis Generator, do not modify.
    -->
    insert into phoneLogin (phone, aKey)
    values (#{phone,jdbcType=VARCHAR}, #{akey,jdbcType=INTEGER})
  </insert>
  <insert id="insertSelective" parameterType="com.cn.ssm.entity.PhoneLogin" >
    <!--
      WARNING - @mbggenerated
      This element is automatically generated by MyBatis Generator, do not modify.
    -->
    insert into phoneLogin
    <trim prefix="(" suffix=")" suffixOverrides="," >
      <if test="phone != null" >
        phone,
      </if>
      <if test="akey != null" >
        aKey,
      </if>
    </trim>
    <trim prefix="values (" suffix=")" suffixOverrides="," >
      <if test="phone != null" >
        #{phone,jdbcType=VARCHAR},
      </if>
      <if test="akey != null" >
        #{akey,jdbcType=INTEGER},
      </if>
    </trim>
  </insert>
  <update id="updateByPrimaryKeySelective" parameterType="com.cn.ssm.entity.PhoneLogin" >
    <!--
      WARNING - @mbggenerated
      This element is automatically generated by MyBatis Generator, do not modify.
    -->
    update phoneLogin
    <set >
      <if test="akey != null" >
        aKey = #{akey,jdbcType=INTEGER},
      </if>
    </set>
    where phone = #{phone,jdbcType=VARCHAR}
  </update>
  <update id="updateByPrimaryKey" parameterType="com.cn.ssm.entity.PhoneLogin" >
    <!--
      WARNING - @mbggenerated
      This element is automatically generated by MyBatis Generator, do not modify.
    -->
    update phoneLogin
    set aKey = #{akey,jdbcType=INTEGER}
    where phone = #{phone,jdbcType=VARCHAR}
  </update>
</mapper>